<?xml version="1.0" encoding="utf-8"?>
<CanvasApp xmlns:xsi="http://www.w3.org/2001/XMLSchema-instance">
  <Name>dora_dorayak_8175f</Name>
  <AppVersion>2022-06-29T09:26:46Z</AppVersion>
  <Status>Ready</Status>
  <CreatedByClientVersion>3.22062.5.0</CreatedByClientVersion>
  <MinClientVersion>3.22062.5.0</MinClientVersion>
  <Tags>{"primaryDeviceWidth":"640","primaryDeviceHeight":"1136","supportsPortrait":"true","supportsLandscape":"true","primaryFormFactor":"Phone","publisherVersion":"3.22062.5","minimumRequiredApiVersion":"2.2.0","hasComponent":"false","hasUnlockedComponent":"false","isUnifiedRootApp":"false","sienaVersion":"20220629T092646Z-3.22062.5.0"}</Tags>
  <IsCdsUpgraded>0</IsCdsUpgraded>
  <GalleryItemId xsi:nil="true"></GalleryItemId>
  <BackgroundColor>RGBA(0,176,240,1)</BackgroundColor>
  <DisplayName>dora-yak</DisplayName>
  <Description xsi:nil="true"></Description>
  <CommitMessage xsi:nil="true"></CommitMessage>
  <Publisher xsi:nil="true"></Publisher>
  <AuthorizationReferences>[]</AuthorizationReferences>
  <ConnectionReferences>{}</ConnectionReferences>
  <DatabaseReferences>{}</DatabaseReferences>
  <AppComponents>[]</AppComponents>
  <AppComponentDependencies>[]</AppComponentDependencies>
  <CanConsumeAppPass>1</CanConsumeAppPass>
  <CanvasAppType>0</CanvasAppType>
  <BypassConsent>0</BypassConsent>
  <AdminControlBypassConsent>0</AdminControlBypassConsent>
  <EmbeddedApp xsi:nil="true"></EmbeddedApp>
  <IntroducedVersion>1.0</IntroducedVersion>
  <CdsDependencies>{"cdsdependencies":[]}</CdsDependencies>
  <IsCustomizable>1</IsCustomizable>
  <BackgroundImageUri>/CanvasApps/dora_dorayak_8175f_BackgroundImageUri</BackgroundImageUri>
  <DocumentUri>/CanvasApps/dora_dorayak_8175f_DocumentUri.msapp</DocumentUri>
</CanvasApp>